nlm_torch_new-0.1.4.dist-info/licenses/LICENSE
torch_nlm/__init__.py
torch_nlm/apply_2d_ops.py
torch_nlm/apply_3d_ops.py
torch_nlm/base_ops.py
nlm_torch_new-0.1.4.dist-info/METADATA
nlm_torch_new-0.1.4.dist-info/WHEEL
nlm_torch_new-0.1.4.dist-info/top_level.txt
nlm_torch_new-0.1.4.dist-info/RECORD
