Metadata-Version: 2.4
Name: nlm-torch-new
Version: 0.1.4
Summary: PyTorch-based implementation of non-local means with GPU support.
Author-email: lucianchauvin <me@lucianchauvin.com>, josegcpa <jose.almeida@research.fchampalimaud.pt>
License-Expression: MIT
Requires-Python: >=3.13
License-File: LICENSE
Requires-Dist: einops>=0.8.1
Requires-Dist: numpy>=2.2.6
Requires-Dist: pillow>=11.2.1
Requires-Dist: pywavelets>=1.8.0
Requires-Dist: scikit-image>=0.25.2
Requires-Dist: torch>=2.7.1
Requires-Dist: tqdm>=4.67.1
Dynamic: license-file
